harc/__init__.py
harc/harc_cli.py
harc/log.json
harc/plugins/__init__.py
harc/plugins/git_password_option.py
harc/plugins/git_username_option.py
harc/plugins/plugin_command.py
harc/plugins/pypi_password_option.py
harc/plugins/pypi_username_option.py
harc/plugins/git/__init__.py
harc/plugins/git/git_release.py
harc/plugins/pypi/__init__.py
harc/plugins/pypi/pypi_deploy.py
harc/plugins/python/__init__.py
harc/plugins/python/python_generate.py
harc/shell/__init__.py
harc/shell/command.py
harc/shell/flag.py
harc/shell/key.py
harc/shell/parameter.py
harc/system/__init__.py
harc/system/exceptions.py
harc/system/git.py
harc/system/profile.py
harc/system/pypi.py
harc/system/utils.py
harc/system/release/__init__.py
harc/system/release/python_release_file.py
harc/system/release/release_file.py
harc/system/release/release_file_factory.py
harc/system/release/release_number.py
harc-1.0.39.dist-info/LICENSE
harc-1.0.39.dist-info/METADATA
harc-1.0.39.dist-info/WHEEL
harc-1.0.39.dist-info/entry_points.txt
harc-1.0.39.dist-info/top_level.txt
harc-1.0.39.dist-info/RECORD
